README.md
setup.py
flask_peewee_swagger/__init__.py
flask_peewee_swagger/swagger.py
flask_peewee_swagger.egg-info/PKG-INFO
flask_peewee_swagger.egg-info/SOURCES.txt
flask_peewee_swagger.egg-info/dependency_links.txt
flask_peewee_swagger.egg-info/not-zip-safe
flask_peewee_swagger.egg-info/requires.txt
flask_peewee_swagger.egg-info/top_level.txt
flask_peewee_swagger/static/swagger-ui-2.2.10/swagger-ui.js
flask_peewee_swagger/static/swagger-ui-2.2.10/swagger-ui.min.js
flask_peewee_swagger/static/swagger-ui-2.2.10/css/print.css
flask_peewee_swagger/static/swagger-ui-2.2.10/css/reset.css
flask_peewee_swagger/static/swagger-ui-2.2.10/css/screen.css
flask_peewee_swagger/static/swagger-ui-2.2.10/css/style.css
flask_peewee_swagger/static/swagger-ui-2.2.10/css/typography.css
flask_peewee_swagger/static/swagger-ui-2.2.10/images/explorer_icons.png
flask_peewee_swagger/static/swagger-ui-2.2.10/images/favicon-16x16.png
flask_peewee_swagger/static/swagger-ui-2.2.10/images/favicon-32x32.png
flask_peewee_swagger/static/swagger-ui-2.2.10/images/logo_small.png
flask_peewee_swagger/static/swagger-ui-2.2.10/images/pet_store_api.png
flask_peewee_swagger/static/swagger-ui-2.2.10/images/wordnik_api.png
flask_peewee_swagger/static/swagger-ui-2.2.10/lib/backbone-min.js
flask_peewee_swagger/static/swagger-ui-2.2.10/lib/es5-shim.js
flask_peewee_swagger/static/swagger-ui-2.2.10/lib/handlebars-4.0.5.js
flask_peewee_swagger/static/swagger-ui-2.2.10/lib/highlight.9.1.0.pack.js
flask_peewee_swagger/static/swagger-ui-2.2.10/lib/highlight.9.1.0.pack_extended.js
flask_peewee_swagger/static/swagger-ui-2.2.10/lib/jquery-1.8.0.min.js
flask_peewee_swagger/static/swagger-ui-2.2.10/lib/jquery.ba-bbq.min.js
flask_peewee_swagger/static/swagger-ui-2.2.10/lib/jquery.slideto.min.js
flask_peewee_swagger/static/swagger-ui-2.2.10/lib/jquery.wiggle.min.js
flask_peewee_swagger/static/swagger-ui-2.2.10/lib/js-yaml.min.js
flask_peewee_swagger/static/swagger-ui-2.2.10/lib/jsoneditor.min.js
flask_peewee_swagger/static/swagger-ui-2.2.10/lib/lodash.min.js
flask_peewee_swagger/static/swagger-ui-2.2.10/lib/marked.js
flask_peewee_swagger/static/swagger-ui-2.2.10/lib/object-assign-pollyfill.js
flask_peewee_swagger/static/swagger-ui-2.2.10/lib/sanitize-html.min.js
