Metadata-Version: 1.1
Name: flask-peewee-swagger
Version: 1.1.5
Summary: Swagger Documentation for flask-peewee apis
Home-page: http://github.com/hapyak/flask-peewee-swagger/
Author: Jason Horman
Author-email: jhorman@hapyak.com
License: BSD
Platform: any
Classifier: Environment :: Web Environment
Classifier: Intended Audience :: Developers
Classifier: License :: OSI Approved :: BSD License
Classifier: Operating System :: OS Independent
Classifier: Programming Language :: Python
Classifier: Topic :: Internet :: WWW/HTTP :: Dynamic Content
Classifier: Topic :: Software Development :: Libraries :: Python Modules
